mlearner/__init__.py
mlearner/classifier/__init__.py
mlearner/classifier/ml_clasifier.py
mlearner/data/__init__.py
mlearner/data/_dummy_dataset.py
mlearner/data/wine.py
mlearner/evaluation/__init__.py
mlearner/evaluation/ml_evaluation.py
mlearner/externals/__init__.py
mlearner/externals/estimator_checks.py
mlearner/feature_selection/__init__.py
mlearner/feature_selection/feature_selection.py
mlearner/images/__init__.py
mlearner/images/load_data_images.py
mlearner/load/__init__.py
mlearner/load/load_file.py
mlearner/models/__init__.py
mlearner/models/ml_CatBoost.py
mlearner/models/ml_LightBoost.py
mlearner/models/ml_XGBoost.py
mlearner/neural/__init__.py
mlearner/neural/ml_neural.py
mlearner/nlp/__init__.py
mlearner/nlp/cnn.py
mlearner/nlp/cnn_advanced.py
mlearner/nlp/helpers.py
mlearner/nlp/transformer.py
mlearner/nlp/transformer_continuos.py
mlearner/nlp/utils.py
mlearner/plotly/__init__.py
mlearner/plotly/ml_plotly.py
mlearner/preprocessing/__init__.py
mlearner/preprocessing/base_preprocess.py
mlearner/preprocessing/droper.py
mlearner/preprocessing/extract_target.py
mlearner/preprocessing/feature_selector.py
mlearner/preprocessing/log_skewed.py
mlearner/preprocessing/mean_centering.py
mlearner/preprocessing/one_hot_encoder.py
mlearner/preprocessing/perfomance_transformers.py
mlearner/preprocessing/reduce_feature.py
mlearner/preprocessing/replace_categorical.py
mlearner/preprocessing/replace_na.py
mlearner/preprocessing/scaling.py
mlearner/stacking/__init__.py
mlearner/stacking/voting.py
mlearner/training/__init__.py
mlearner/training/ml_Training.py
mlearner/utils/__init__.py
mlearner/utils/keras.py
mlearner/utils/params_manager.py
mlearner-0.2.8.dist-info/LICENSE
mlearner-0.2.8.dist-info/METADATA
mlearner-0.2.8.dist-info/WHEEL
mlearner-0.2.8.dist-info/top_level.txt
mlearner-0.2.8.dist-info/RECORD
