Metadata-Version: 2.1
Name: mlearner
Version: 0.2.8
Summary: Machine Learning Library Extensions
Home-page: https://github.com/jaisenbe58r/MLearner
Author: Jaime Sendra
Author-email: jaisenberafel@gmail.com
License: MIT
Download-URL: https://github.com/jaisenbe58r/MLearner/archive/v0.0.2.tar.gz
Keywords: SOME,MEANINGFULL,KEYWORDS
Platform: any
Classifier: Development Status :: 3 - Alpha
Classifier: Intended Audience :: Developers
Classifier: Topic :: Software Development :: Build Tools
Classifier: License :: OSI Approved :: MIT License
Classifier: Programming Language :: Python :: 3
Classifier: Programming Language :: Python :: 3.6
Classifier: Programming Language :: Python :: 3.7
Classifier: Programming Language :: Python :: 3.8
Classifier: Operating System :: Microsoft :: Windows
Classifier: Operating System :: POSIX
Classifier: Operating System :: Unix
Classifier: Operating System :: MacOS
Classifier: Programming Language :: Python :: 3.7
Classifier: Topic :: Scientific/Engineering
Classifier: Topic :: Scientific/Engineering :: Artificial Intelligence
Classifier: Topic :: Scientific/Engineering :: Information Analysis
Classifier: Topic :: Scientific/Engineering :: Image Recognition
Requires-Python: >=3.6
Requires-Dist: Flask
Requires-Dist: scikit-learn (==0.22.2)
Requires-Dist: matplotlib (>=3.1.1)
Requires-Dist: pandas (>=0.25.0)
Requires-Dist: numpy
Requires-Dist: seaborn
Requires-Dist: shap
Requires-Dist: hyperopt
Requires-Dist: scipy
Requires-Dist: xgboost
Requires-Dist: lightgbm
Requires-Dist: catboost
Requires-Dist: pytest (<5.0.0,>=4.6.6)
Requires-Dist: pytest-cov
Requires-Dist: codacy-coverage
Requires-Dist: tqdm
Requires-Dist: emoji
Requires-Dist: mkdocs
Requires-Dist: setuptools
